gtap_extractor/__init__.py
gtap_extractor/main.py
gtap_extractor/extraction/__init__.py
gtap_extractor/extraction/extractor.py
gtap_extractor/gtap_mrio/__init__.py
gtap_extractor/gtap_mrio/mrio_builder.py
gtap_extractor-0.1.1.dist-info/LICENSE
gtap_extractor-0.1.1.dist-info/METADATA
gtap_extractor-0.1.1.dist-info/WHEEL
gtap_extractor-0.1.1.dist-info/top_level.txt
gtap_extractor-0.1.1.dist-info/RECORD
