Metadata-Version: 2.1
Name: gtap-extractor
Version: 0.1.1
Summary: Extract GTAP data from .har files and save it as .nc file.
Home-page: https://gitlab.pik-potsdam.de/mrio_toolbox/gtap_extractor
Author: Timothe Beaufils
Author-email: timothe.beaufils@pik-potsdam.de
Keywords: GTAP,MRIO,Input-Output,Economics,Industrial Ecology,netcdf,International Trade
Classifier: Programming Language :: Python :: 3
Classifier: License :: OSI Approved :: GNU Affero General Public License v3
Classifier: Operating System :: OS Independent
License-File: LICENSE
Requires-Dist: netcdf4
Requires-Dist: xarray
Requires-Dist: mrio-toolbox
